{
    "data": {
      "description": "Defense Notice\nThis is to notify the intern students that their Online Internship Defense will be held in Google Meet. Google Meet Class Code is uhbpkkq and Google Meet Link is uns-dwmy-vhr\n \n \nProf. Dr. Md. Ali NoorDirectorMBA Program",
      "downloads": [
        {
          "url": ""
        }
      ],
      "images": [
        {
          "url": ""
        }
      ],
      "pubDate": "8 Oct 2021",
      "title": "Defense Notice"
    },
    "status": "success"
  }